HbaseShujukuRumenjiaochengCYuyanBianchengWang/README.md
HbaseShujukuRumenjiaochengCYuyanBianchengWang/__init__.py
HbaseShujukuRumenjiaochengCYuyanBianchengWang/__main__.py
HbaseShujukuRumenjiaochengCYuyanBianchengWang/file.epub
HbaseShujukuRumenjiaochengCYuyanBianchengWang/index.html
HbaseShujukuRumenjiaochengCYuyanBianchengWang/css/__init__.py
HbaseShujukuRumenjiaochengCYuyanBianchengWang/css/annotations.css
HbaseShujukuRumenjiaochengCYuyanBianchengWang/css/main.css
HbaseShujukuRumenjiaochengCYuyanBianchengWang/css/normalize.css
HbaseShujukuRumenjiaochengCYuyanBianchengWang/css/popup.css
HbaseShujukuRumenjiaochengCYuyanBianchengWang/font/__init__.py
HbaseShujukuRumenjiaochengCYuyanBianchengWang/font/fontello.eot
HbaseShujukuRumenjiaochengCYuyanBianchengWang/font/fontello.svg
HbaseShujukuRumenjiaochengCYuyanBianchengWang/font/fontello.ttf
HbaseShujukuRumenjiaochengCYuyanBianchengWang/font/fontello.woff
HbaseShujukuRumenjiaochengCYuyanBianchengWang/img/__init__.py
HbaseShujukuRumenjiaochengCYuyanBianchengWang/img/annotator-glyph-sprite.png
HbaseShujukuRumenjiaochengCYuyanBianchengWang/img/annotator-icon-sprite.png
HbaseShujukuRumenjiaochengCYuyanBianchengWang/img/apple-touch-icon.png
HbaseShujukuRumenjiaochengCYuyanBianchengWang/img/cancelfullscreen.png
HbaseShujukuRumenjiaochengCYuyanBianchengWang/img/close.png
HbaseShujukuRumenjiaochengCYuyanBianchengWang/img/fullscreen.png
HbaseShujukuRumenjiaochengCYuyanBianchengWang/img/loader.gif
HbaseShujukuRumenjiaochengCYuyanBianchengWang/img/menu-icon.png
HbaseShujukuRumenjiaochengCYuyanBianchengWang/img/save.png
HbaseShujukuRumenjiaochengCYuyanBianchengWang/img/saved.png
HbaseShujukuRumenjiaochengCYuyanBianchengWang/img/settings-s.png
HbaseShujukuRumenjiaochengCYuyanBianchengWang/img/settings.png
HbaseShujukuRumenjiaochengCYuyanBianchengWang/img/star.png
HbaseShujukuRumenjiaochengCYuyanBianchengWang/js/__init__.py
HbaseShujukuRumenjiaochengCYuyanBianchengWang/js/epub.js
hbase_shujuku_rumenjiaocheng_c_yuyan_biancheng_wang-2024.3.4.0.dist-info/METADATA
hbase_shujuku_rumenjiaocheng_c_yuyan_biancheng_wang-2024.3.4.0.dist-info/WHEEL
hbase_shujuku_rumenjiaocheng_c_yuyan_biancheng_wang-2024.3.4.0.dist-info/entry_points.txt
hbase_shujuku_rumenjiaocheng_c_yuyan_biancheng_wang-2024.3.4.0.dist-info/top_level.txt
hbase_shujuku_rumenjiaocheng_c_yuyan_biancheng_wang-2024.3.4.0.dist-info/RECORD
